create_mountaineer_app/__init__.py
create_mountaineer_app/builder.py
create_mountaineer_app/cli.py
create_mountaineer_app/enums.py
create_mountaineer_app/external.py
create_mountaineer_app/generation.py
create_mountaineer_app/io.py
create_mountaineer_app/__tests__/__init__.py
create_mountaineer_app/__tests__/common.py
create_mountaineer_app/__tests__/test_builder.py
create_mountaineer_app/__tests__/test_cli.py
create_mountaineer_app/__tests__/test_generation.py
create_mountaineer_app/__tests__/environments/__init__.py
create_mountaineer_app/__tests__/environments/common.py
create_mountaineer_app/__tests__/environments/test_poetry.py
create_mountaineer_app/__tests__/environments/test_uv.py
create_mountaineer_app/__tests__/environments/test_venv.py
create_mountaineer_app/environments/__init__.py
create_mountaineer_app/environments/base.py
create_mountaineer_app/environments/poetry.py
create_mountaineer_app/environments/uv.py
create_mountaineer_app/environments/venv.py
create_mountaineer_app/templates/__init__.py
create_mountaineer_app/templates/.zed/settings.json
create_mountaineer_app/templates/editor_configs/vim/.vimrc
create_mountaineer_app/templates/editor_configs/vscode/.vscode/settings.json
create_mountaineer_app/templates/project/.dockerignore
create_mountaineer_app/templates/project/.gitignore
create_mountaineer_app/templates/project/Dockerfile
create_mountaineer_app/templates/project/README.md
create_mountaineer_app/templates/project/docker-compose.yml
create_mountaineer_app/templates/project/pyproject.toml
create_mountaineer_app/templates/project/[project_name]/__init__.py
create_mountaineer_app/templates/project/[project_name]/app.py
create_mountaineer_app/templates/project/[project_name]/cli.py
create_mountaineer_app/templates/project/[project_name]/config.py
create_mountaineer_app/templates/project/[project_name]/main.py
create_mountaineer_app/templates/project/[project_name]/__tests__/__init__.py
create_mountaineer_app-0.10.1.dist-info/METADATA
create_mountaineer_app-0.10.1.dist-info/WHEEL
create_mountaineer_app-0.10.1.dist-info/entry_points.txt
create_mountaineer_app-0.10.1.dist-info/RECORD
