Metadata-Version: 2.4
Name: create-mountaineer-app
Version: 0.10.1
Summary: Easily get started with a new Mountaineer project.
Author-email: Pierce Freeman <pierce@freeman.vc>
Requires-Python: <3.14,>=3.10
Requires-Dist: click>=8.1.8
Requires-Dist: jinja2>=3.1.6
Requires-Dist: pydantic>=2.10.6
Requires-Dist: questionary>=2.1.0
Requires-Dist: toml>=0.10.2
